{
  "uuid": "blog-post-app-ai-webdev-002",
  "appType": "WebAppProps",
  "appSecondaryType": "website",
  "name": "AI in Web Development Blog Post",
  "alias": "ai-web-development-post",
  "summary": "A comprehensive blog post exploring the transformative role of AI in modern web development. Covers AI-powered code completion, automated testing, design tools, and practical applications. Features real-world examples, code snippets, and insights into the future of AI-assisted development.",
  "shortSummary": "Exploring how AI is revolutionizing web development with practical examples and future insights",
  "lastUpdatedEpoch": 1731225600,
  "languages": [
    {
      "code": "en",
      "nameEnglish": "English",
      "nameNative": "English",
      "isDefault": true
    }
  ],
  "layout": "wide",
  "menuPosition": "HeaderMenuTop",
  "theme": {
    "light": {
      "background": "#ffffff",
      "foreground": "#0a0a0a",
      "primary": "#1e3a8a",
      "primary-foreground": "#ffffff",
      "secondary": "#f3f4f6",
      "secondary-foreground": "#111827",
      "muted": "#f9fafb",
      "muted-foreground": "#6b7280",
      "accent": "#a78bfa",
      "accent-foreground": "#ffffff",
      "destructive": "#ef4444",
      "destructive-foreground": "#ffffff",
      "border": "#e5e7eb",
      "input": "#e5e7eb",
      "ring": "#8b5cf6"
    },
    "dark": {
      "background": "#0a0a0a",
      "foreground": "#f9fafb",
      "primary": "#a78bfa",
      "primary-foreground": "#1f2937",
      "secondary": "#1f2937",
      "secondary-foreground": "#f9fafb",
      "muted": "#111827",
      "muted-foreground": "#9ca3af",
      "accent": "#c4b5fd",
      "accent-foreground": "#1f2937",
      "destructive": "#dc2626",
      "destructive-foreground": "#f9fafb",
      "border": "#374151",
      "input": "#374151",
      "ring": "#a78bfa"
    },
    "fonts": {
      "body": {
        "family": "Inter",
        "variant": "regular",
        "url": "https://fonts.googleapis.com/css2?family=Inter:wght@400&display=swap"
      },
      "heading": {
        "family": "Inter",
        "variant": "700",
        "url": "https://fonts.googleapis.com/css2?family=Inter:wght@700&display=swap"
      }
    },
    "radius": "0.5rem",
    "metadata": {
      "title": "AI in Web Development: The Future is Now - Tech Blog",
      "description": "Discover how artificial intelligence is transforming web development. Learn about AI-powered tools, automated coding, intelligent testing, and the future of development.",
      "keywords": "ai, artificial intelligence, web development, machine learning, automation, coding tools, ai tools"
    }
  },
  "sidebar": [],
  "header": [
    {
      "uuid": "navbar-blog-post-002",
      "componentType": "NavbarProps",
      "sticky": true,
      "variant": "default",
      "menuVariant": "default",
      "classes": "border-b",
      "logo": {
        "uuid": "logo-blog-002",
        "componentType": "NavbarLogoProps",
        "type": "text",
        "text": "Tech Blog",
        "href": {
          "componentType": "LinkProps",
          "uuid": "logo-blog-href-002",
          "href": "/",
          "text": "Tech Blog"
        }
      },
      "content": [
        {
          "uuid": "nav-home-002",
          "componentType": "MenuLinkItemProps",
          "type": "link",
          "label": "Home",
          "href": {
            "uuid": "nav-home-link-002",
            "componentType": "LinkProps",
            "href": "/",
            "text": "Home"
          }
        },
        {
          "uuid": "nav-blog-003",
          "componentType": "MenuLinkItemProps",
          "type": "link",
          "label": "Blog",
          "href": {
            "uuid": "nav-blog-link-003",
            "componentType": "LinkProps",
            "href": "/blog",
            "text": "Blog"
          }
        },
        {
          "uuid": "nav-about-004",
          "componentType": "MenuLinkItemProps",
          "type": "link",
          "label": "About",
          "href": {
            "uuid": "nav-about-link-004",
            "componentType": "LinkProps",
            "href": "/about",
            "text": "About"
          }
        }
      ]
    }
  ],
  "footer": [
    {
      "uuid": "footer-section-002",
      "componentType": "SectionProps",
      "sectionSlug": "footer-section-002",
      "classes": "border-t bg-muted/50",
      "spacing": "lg",
      "content": [
        {
          "uuid": "footer-flex-003",
          "componentType": "FlexProps",
          "direction": "column",
          "gap": "8",
          "content": [
            {
              "uuid": "footer-grid-004",
              "componentType": "GridProps",
              "columns": 4,
              "gap": "8",
              "content": [
                {
                  "uuid": "footer-col1-005",
                  "componentType": "FlexProps",
                  "direction": "column",
                  "gap": "4",
                  "content": [
                    {
                      "uuid": "footer-brand-006",
                      "componentType": "HeadingProps",
                      "level": 3,
                      "text": "Tech Blog"
                    },
                    {
                      "uuid": "footer-desc-007",
                      "componentType": "TextProps",
                      "content": "Your trusted source for web development tutorials, programming tips, and technology insights.",
                      "classes": "text-muted-foreground"
                    }
                  ]
                },
                {
                  "uuid": "footer-col2-008",
                  "componentType": "FlexProps",
                  "direction": "column",
                  "gap": "4",
                  "content": [
                    {
                      "uuid": "footer-links-heading-009",
                      "componentType": "HeadingProps",
                      "level": 4,
                      "text": "Content"
                    },
                    {
                      "uuid": "footer-link-blog-010",
                      "componentType": "LinkProps",
                      "href": "/blog",
                      "text": "Blog",
                      "classes": "text-muted-foreground hover:text-foreground"
                    },
                    {
                      "uuid": "footer-link-tutorials-011",
                      "componentType": "LinkProps",
                      "href": "/tutorials",
                      "text": "Tutorials",
                      "classes": "text-muted-foreground hover:text-foreground"
                    },
                    {
                      "uuid": "footer-link-guides-012",
                      "componentType": "LinkProps",
                      "href": "/guides",
                      "text": "Guides",
                      "classes": "text-muted-foreground hover:text-foreground"
                    }
                  ]
                },
                {
                  "uuid": "footer-col3-013",
                  "componentType": "FlexProps",
                  "direction": "column",
                  "gap": "4",
                  "content": [
                    {
                      "uuid": "footer-company-heading-014",
                      "componentType": "HeadingProps",
                      "level": 4,
                      "text": "Company"
                    },
                    {
                      "uuid": "footer-link-about-015",
                      "componentType": "LinkProps",
                      "href": "/about",
                      "text": "About",
                      "classes": "text-muted-foreground hover:text-foreground"
                    },
                    {
                      "uuid": "footer-link-contact-016",
                      "componentType": "LinkProps",
                      "href": "/contact",
                      "text": "Contact",
                      "classes": "text-muted-foreground hover:text-foreground"
                    }
                  ]
                },
                {
                  "uuid": "footer-col4-017",
                  "componentType": "FlexProps",
                  "direction": "column",
                  "gap": "4",
                  "content": [
                    {
                      "uuid": "footer-social-heading-018",
                      "componentType": "HeadingProps",
                      "level": 4,
                      "text": "Follow Us"
                    },
                    {
                      "uuid": "footer-social-019",
                      "componentType": "FlexProps",
                      "direction": "row",
                      "gap": "3",
                      "content": [
                        {
                          "uuid": "footer-twitter-020",
                          "componentType": "LinkProps",
                          "href": "https://twitter.com",
                          "text": "𝕏",
                          "classes": "text-muted-foreground hover:text-foreground"
                        },
                        {
                          "uuid": "footer-github-021",
                          "componentType": "LinkProps",
                          "href": "https://github.com",
                          "text": "GitHub",
                          "classes": "text-muted-foreground hover:text-foreground"
                        },
                        {
                          "uuid": "footer-linkedin-022",
                          "componentType": "LinkProps",
                          "href": "https://linkedin.com",
                          "text": "LinkedIn",
                          "classes": "text-muted-foreground hover:text-foreground"
                        }
                      ]
                    }
                  ]
                }
              ]
            },
            {
              "uuid": "footer-divider-023",
              "componentType": "SpacerProps",
              "size": "md"
            },
            {
              "uuid": "footer-copyright-024",
              "componentType": "TextProps",
              "content": "© 2024 Tech Blog. All rights reserved.",
              "classes": "text-center text-muted-foreground text-sm"
            }
          ]
        }
      ]
    }
  ],
  "pages": [
    {
      "uuid": "blogpost-002-ai-webdev",
      "pageType": "BlogPostPageProps",
      "title": "AI in Web Development: The Future is Now",
      "slug": "ai-in-web-development",
      "summary": "Explore how artificial intelligence is revolutionizing web development. From AI-powered code completion tools like GitHub Copilot to automated testing and intelligent design systems, discover how AI is transforming the way we build for the web. Learn about practical applications, real-world examples, and what the future holds for AI-assisted development.",
      "shortSummary": "Discover how AI is transforming web development with intelligent tools and automation",
      "lastUpdatedEpoch": 1731225600,
      "metadata": {
        "title": "AI in Web Development: The Future is Now",
        "description": "Discover how artificial intelligence is transforming web development. Learn about AI-powered coding tools, automated testing, intelligent design systems, and the future of development.",
        "keywords": "ai, artificial intelligence, web development, github copilot, machine learning, automation, ai tools, coding assistant",
        "openGraph": {
          "type": "article"
        }
      },
      "content": [
        {
          "uuid": "hero-section-100",
          "componentType": "SectionProps",
          "sectionSlug": "hero-section-100",
          "spacing": "xl",
          "classes": "bg-gradient-to-b from-primary/5 to-background border-b",
          "content": [
            {
              "uuid": "hero-container-101",
              "componentType": "CenterProps",
              "content": [
                {
                  "uuid": "hero-flex-102",
                  "componentType": "FlexProps",
                  "direction": "column",
                  "gap": "6",
                  "classes": "py-12 text-center",
                  "content": [
                    {
                      "uuid": "breadcrumb-103",
                      "componentType": "FlexProps",
                      "direction": "row",
                      "gap": "2",
                      "justify": "center",
                      "align": "center",
                      "classes": "text-sm text-muted-foreground",
                      "content": [
                        {
                          "uuid": "breadcrumb-home-104",
                          "componentType": "LinkProps",
                          "href": "/",
                          "text": "Home",
                          "classes": "hover:text-foreground"
                        },
                        {
                          "uuid": "breadcrumb-sep-105",
                          "componentType": "TextProps",
                          "content": "/"
                        },
                        {
                          "uuid": "breadcrumb-blog-106",
                          "componentType": "LinkProps",
                          "href": "/blog",
                          "text": "Blog",
                          "classes": "hover:text-foreground"
                        },
                        {
                          "uuid": "breadcrumb-sep-107",
                          "componentType": "TextProps",
                          "content": "/"
                        },
                        {
                          "uuid": "breadcrumb-current-108",
                          "componentType": "TextProps",
                          "content": "Technology"
                        }
                      ]
                    },
                    {
                      "uuid": "post-title-109",
                      "componentType": "HeadingProps",
                      "level": 1,
                      "text": "AI in Web Development: The Future is Now",
                      "classes": "text-4xl md:text-5xl lg:text-6xl font-bold tracking-tight"
                    },
                    {
                      "uuid": "post-meta-110",
                      "componentType": "FlexProps",
                      "direction": "row",
                      "gap": "4",
                      "justify": "center",
                      "align": "center",
                      "classes": "text-muted-foreground flex-wrap",
                      "content": [
                        {
                          "uuid": "author-meta-111",
                          "componentType": "FlexProps",
                          "direction": "row",
                          "gap": "2",
                          "align": "center",
                          "content": [
                            {
                              "uuid": "author-icon-112",
                              "componentType": "IconProps",
                              "name": "user",
                              "size": 16
                            },
                            {
                              "uuid": "author-name-113",
                              "componentType": "TextProps",
                              "content": "Alex Chen"
                            }
                          ]
                        },
                        {
                          "uuid": "date-meta-114",
                          "componentType": "FlexProps",
                          "direction": "row",
                          "gap": "2",
                          "align": "center",
                          "content": [
                            {
                              "uuid": "date-icon-115",
                              "componentType": "IconProps",
                              "name": "calendar",
                              "size": 16
                            },
                            {
                              "uuid": "date-text-116",
                              "componentType": "TextProps",
                              "content": "November 10, 2024"
                            }
                          ]
                        },
                        {
                          "uuid": "readtime-meta-117",
                          "componentType": "FlexProps",
                          "direction": "row",
                          "gap": "2",
                          "align": "center",
                          "content": [
                            {
                              "uuid": "clock-icon-118",
                              "componentType": "IconProps",
                              "name": "clock",
                              "size": 16
                            },
                            {
                              "uuid": "readtime-text-119",
                              "componentType": "TextProps",
                              "content": "10 min read"
                            }
                          ]
                        }
                      ]
                    },
                    {
                      "uuid": "tags-120",
                      "componentType": "FlexProps",
                      "direction": "row",
                      "gap": "2",
                      "justify": "center",
                      "classes": "flex-wrap",
                      "content": [
                        {
                          "uuid": "tag-ai-121",
                          "componentType": "BadgeProps",
                          "variant": "default",
                          "content": "AI"
                        },
                        {
                          "uuid": "tag-ml-122",
                          "componentType": "BadgeProps",
                          "variant": "secondary",
                          "content": "Machine Learning"
                        },
                        {
                          "uuid": "tag-webdev-123",
                          "componentType": "BadgeProps",
                          "variant": "outline",
                          "content": "Web Development"
                        },
                        {
                          "uuid": "tag-automation-124",
                          "componentType": "BadgeProps",
                          "variant": "secondary",
                          "content": "Automation"
                        }
                      ]
                    }
                  ]
                }
              ]
            }
          ]
        },
        {
          "uuid": "featured-image-125",
          "componentType": "SectionProps",
          "sectionSlug": "featured-image-125",
          "spacing": "sm",
          "content": [
            {
              "uuid": "image-container-126",
              "componentType": "CenterProps",
              "content": [
                {
                  "uuid": "featured-img-127",
                  "componentType": "ImageProps",
                  "src": "https://images.unsplash.com/photo-1677442136019-21780ecad995?w=1200&h=600&fit=crop",
                  "alt": "AI and code visualization representing artificial intelligence in development",
                  "classes": "w-full h-[400px] object-cover rounded-lg shadow-lg",
                  "asset": {
                    "uuid": "featured-img-127-asset",
                    "componentType": "ImageAssetProps",
                    "isProcessed": false,
                    "keywords": "blog, technology, web development, programming",
                    "requestedWidth": 1200,
                    "requestedHeight": 600
                  }
                }
              ]
            }
          ]
        },
        {
          "uuid": "article-content-128",
          "componentType": "SectionProps",
          "sectionSlug": "article-content-128",
          "spacing": "xl",
          "content": [
            {
              "uuid": "content-container-129",
              "componentType": "CenterProps",
              "content": [
                {
                  "uuid": "content-flex-130",
                  "componentType": "FlexProps",
                  "direction": "column",
                  "gap": "8",
                  "classes": "prose prose-lg dark:prose-invert max-w-none",
                  "content": [
                    {
                      "uuid": "intro-131",
                      "componentType": "MarkdownBlockProps",
                      "content": "Artificial Intelligence is no longer a futuristic concept—it's here, and it's fundamentally changing how we build for the web. From intelligent code completion to automated testing and design generation, AI-powered tools are making developers more productive, creative, and efficient than ever before.",
                      "sanitize": true
                    },
                    {
                      "uuid": "revolution-heading-132",
                      "componentType": "HeadingProps",
                      "level": 2,
                      "text": "The AI Revolution in Development"
                    },
                    {
                      "uuid": "revolution-content-133",
                      "componentType": "MarkdownBlockProps",
                      "content": "The integration of AI into web development represents one of the most significant shifts in our industry. We're witnessing a transformation in how code is written, tested, and deployed. AI assistants can now understand context, suggest complete functions, detect bugs before they happen, and even help with architecture decisions.\n\nThis revolution isn't about replacing developers—it's about augmenting their capabilities and freeing them to focus on creative problem-solving and innovation.",
                      "sanitize": true
                    },
                    {
                      "uuid": "tools-heading-134",
                      "componentType": "HeadingProps",
                      "level": 2,
                      "text": "AI-Powered Development Tools"
                    },
                    {
                      "uuid": "copilot-heading-135",
                      "componentType": "HeadingProps",
                      "level": 3,
                      "text": "1. Code Completion and Generation"
                    },
                    {
                      "uuid": "copilot-content-136",
                      "componentType": "MarkdownBlockProps",
                      "content": "Tools like GitHub Copilot, Amazon CodeWhisperer, and Tabnine use machine learning models trained on billions of lines of code to provide intelligent suggestions as you type. These tools understand context, coding patterns, and even your specific codebase style.",
                      "sanitize": true
                    },
                    {
                      "uuid": "code-example-137",
                      "componentType": "MarkdownBlockProps",
                      "content": "```javascript\n// With AI assistance, you can write a comment and get implementation suggestions\n\n// Function to fetch user data with retry logic and exponential backoff\nasync function fetchUserWithRetry(userId, maxRetries = 3) {\n  let retries = 0;\n  let delay = 1000;\n  \n  while (retries < maxRetries) {\n    try {\n      const response = await fetch(`/api/users/${userId}`);\n      if (!response.ok) throw new Error('Failed to fetch');\n      return await response.json();\n    } catch (error) {\n      retries++;\n      if (retries >= maxRetries) throw error;\n      await new Promise(resolve => setTimeout(resolve, delay));\n      delay *= 2; // Exponential backoff\n    }\n  }\n}\n```",
                      "sanitize": false
                    },
                    {
                      "uuid": "testing-heading-138",
                      "componentType": "HeadingProps",
                      "level": 3,
                      "text": "2. Automated Testing"
                    },
                    {
                      "uuid": "testing-content-139",
                      "componentType": "MarkdownBlockProps",
                      "content": "AI can analyze your code and automatically generate comprehensive test suites. Tools like Testim and Mabl use machine learning to create, maintain, and heal tests automatically, reducing the time spent on test maintenance.",
                      "sanitize": true
                    },
                    {
                      "uuid": "code-testing-140",
                      "componentType": "MarkdownBlockProps",
                      "content": "```javascript\n// AI can generate comprehensive test cases from your functions\n\ndescribe('fetchUserWithRetry', () => {\n  it('should successfully fetch user data on first try', async () => {\n    global.fetch = jest.fn(() =>\n      Promise.resolve({\n        ok: true,\n        json: () => Promise.resolve({ id: 1, name: 'John' })\n      })\n    );\n    \n    const result = await fetchUserWithRetry(1);\n    expect(result).toEqual({ id: 1, name: 'John' });\n    expect(fetch).toHaveBeenCalledTimes(1);\n  });\n  \n  it('should retry on failure with exponential backoff', async () => {\n    let attempts = 0;\n    global.fetch = jest.fn(() => {\n      attempts++;\n      if (attempts < 3) {\n        return Promise.reject(new Error('Network error'));\n      }\n      return Promise.resolve({\n        ok: true,\n        json: () => Promise.resolve({ id: 1, name: 'John' })\n      });\n    });\n    \n    const result = await fetchUserWithRetry(1);\n    expect(fetch).toHaveBeenCalledTimes(3);\n  });\n});\n```",
                      "sanitize": false
                    },
                    {
                      "uuid": "design-heading-141",
                      "componentType": "HeadingProps",
                      "level": 3,
                      "text": "3. AI-Powered Design Systems"
                    },
                    {
                      "uuid": "design-content-142",
                      "componentType": "MarkdownBlockProps",
                      "content": "AI tools like Vercel's v0, Galileo AI, and Uizard can transform text descriptions or sketches into functional UI components. These tools understand design principles, accessibility requirements, and can generate production-ready code.",
                      "sanitize": true
                    },
                    {
                      "uuid": "code-generation-heading-143",
                      "componentType": "HeadingProps",
                      "level": 3,
                      "text": "4. Intelligent Code Review"
                    },
                    {
                      "uuid": "code-review-content-144",
                      "componentType": "MarkdownBlockProps",
                      "content": "AI-powered code review tools can identify security vulnerabilities, performance issues, and code smells before they make it to production. They learn from your codebase and provide increasingly relevant suggestions over time.",
                      "sanitize": true
                    },
                    {
                      "uuid": "alert-security-145",
                      "componentType": "FlexProps",
                      "classes": "border-destructive bg-destructive/10",
                      "content": [
                        {
                          "uuid": "alert-title-146",
                          "componentType": "HeadingProps",
                          "level": 4,
                          "text": "⚠️ Security Note"
                        },
                        {
                          "uuid": "alert-desc-147",
                          "componentType": "TextProps",
                          "content": "Always review AI-generated code for security vulnerabilities. AI tools are powerful assistants, but they should not replace human judgment, especially for security-critical code."
                        }
                      ],
                      "direction": "column",
                      "gap": "4"
                    },
                    {
                      "uuid": "practical-heading-148",
                      "componentType": "HeadingProps",
                      "level": 2,
                      "text": "Practical Applications"
                    },
                    {
                      "uuid": "practical-content-149",
                      "componentType": "MarkdownBlockProps",
                      "content": "Here are some real-world applications where AI is making a significant impact:\n\n**1. Rapid Prototyping**\nAI can help you quickly build MVPs and prototypes by generating boilerplate code, component structures, and even entire features from descriptions.\n\n**2. Documentation Generation**\nAI tools can analyze your code and automatically generate comprehensive documentation, API references, and usage examples.\n\n**3. Code Migration**\nAI can assist in migrating codebases between frameworks or languages, understanding patterns and translating them accurately.\n\n**4. Accessibility Improvements**\nAI tools can scan your application and suggest accessibility improvements, ensuring WCAG compliance automatically.\n\n**5. Performance Optimization**\nAI can analyze your application's performance characteristics and suggest optimizations based on best practices and patterns.",
                      "sanitize": true
                    },
                    {
                      "uuid": "example-card-150",
                      "componentType": "FlexProps",
                      "classes": "bg-muted/50 border-2",
                      "content": [
                        {
                          "uuid": "example-flex-151",
                          "componentType": "FlexProps",
                          "direction": "column",
                          "gap": "4",
                          "classes": "p-6",
                          "content": [
                            {
                              "uuid": "example-heading-152",
                              "componentType": "HeadingProps",
                              "level": 4,
                              "text": "Real-World Success Story"
                            },
                            {
                              "uuid": "example-text-153",
                              "componentType": "TextProps",
                              "content": "A mid-size startup reported a 40% reduction in development time after integrating AI-powered coding assistants into their workflow. They found that developers spent less time on boilerplate code and repetitive tasks, allowing them to focus on complex problem-solving and innovation.",
                              "classes": "text-muted-foreground"
                            }
                          ]
                        }
                      ],
                      "direction": "column",
                      "gap": "4"
                    },
                    {
                      "uuid": "challenges-heading-154",
                      "componentType": "HeadingProps",
                      "level": 2,
                      "text": "Challenges and Considerations"
                    },
                    {
                      "uuid": "challenges-content-155",
                      "componentType": "MarkdownBlockProps",
                      "content": "While AI brings tremendous benefits, it's important to be aware of potential challenges:\n\n**Code Quality Concerns**\nAI-generated code may not always follow your team's conventions or best practices. Always review and refactor as needed.\n\n**Over-Reliance**\nThere's a risk of developers becoming too dependent on AI tools and losing fundamental coding skills. Balance is key.\n\n**Security and Privacy**\nBe cautious about what code you allow AI tools to access, especially with proprietary or sensitive codebases.\n\n**Learning Curve**\nEffectively using AI tools requires learning how to communicate with them through prompts and understanding their limitations.\n\n**Cost Considerations**\nMany advanced AI tools come with subscription costs that can add up, especially for larger teams.",
                      "sanitize": true
                    },
                    {
                      "uuid": "best-practices-heading-156",
                      "componentType": "HeadingProps",
                      "level": 2,
                      "text": "Best Practices for AI-Assisted Development"
                    },
                    {
                      "uuid": "alert-best-practices-157",
                      "componentType": "FlexProps",
                      "classes": "border-primary/20 bg-primary/5",
                      "content": [
                        {
                          "uuid": "alert-title-158",
                          "componentType": "HeadingProps",
                          "level": 4,
                          "text": "💡 Pro Tips"
                        },
                        {
                          "uuid": "alert-desc-159",
                          "componentType": "TextProps",
                          "content": "Use AI tools as intelligent assistants, not replacements. The best results come from combining AI capabilities with human expertise and judgment."
                        }
                      ],
                      "direction": "column",
                      "gap": "4"
                    },
                    {
                      "uuid": "best-practices-content-160",
                      "componentType": "MarkdownBlockProps",
                      "content": "To get the most out of AI in your development workflow:\n\n1. **Start Small**: Begin with code completion and gradually adopt more advanced AI tools\n2. **Review Everything**: Always review and understand AI-generated code before using it\n3. **Provide Context**: Give AI tools clear, descriptive prompts with relevant context\n4. **Set Guidelines**: Establish team guidelines for using AI tools responsibly\n5. **Keep Learning**: Stay updated on new AI tools and capabilities\n6. **Test Thoroughly**: AI-generated code should go through the same testing rigor as human-written code\n7. **Document Decisions**: Document when and why you chose to use or modify AI suggestions",
                      "sanitize": true
                    },
                    {
                      "uuid": "future-heading-161",
                      "componentType": "HeadingProps",
                      "level": 2,
                      "text": "The Future of AI in Web Development"
                    },
                    {
                      "uuid": "future-content-162",
                      "componentType": "MarkdownBlockProps",
                      "content": "The future of AI in web development is incredibly exciting. We're moving towards:\n\n**Natural Language Programming**\nDescribe what you want in plain language, and AI will generate the implementation.\n\n**Self-Healing Applications**\nApps that can detect and fix issues automatically without human intervention.\n\n**Personalized User Experiences**\nAI will enable websites to adapt in real-time to individual user preferences and behaviors.\n\n**Automated Optimization**\nContinuous performance and SEO optimization powered by AI analysis.\n\n**Enhanced Collaboration**\nAI tools that facilitate better communication and collaboration between designers, developers, and stakeholders.",
                      "sanitize": true
                    },
                    {
                      "uuid": "conclusion-163",
                      "componentType": "HeadingProps",
                      "level": 2,
                      "text": "Conclusion"
                    },
                    {
                      "uuid": "conclusion-content-164",
                      "componentType": "MarkdownBlockProps",
                      "content": "AI is not just changing web development—it's revolutionizing it. The tools available today are just the beginning of what's possible. As AI technology continues to evolve, we'll see even more powerful capabilities that will make development faster, more accessible, and more creative.\n\nThe key is to embrace these tools while maintaining a critical eye and continuing to develop our core skills. AI is here to augment our abilities, not replace them. Developers who learn to effectively collaborate with AI will be best positioned to thrive in this new era of web development.\n\nThe future is already here—it's time to start building with AI. 🚀",
                      "sanitize": true
                    }
                  ]
                }
              ]
            }
          ]
        },
        {
          "uuid": "cta-section-165",
          "componentType": "SectionProps",
          "sectionSlug": "cta-section-165",
          "spacing": "xl",
          "classes": "bg-muted/50 border-y",
          "content": [
            {
              "uuid": "cta-container-166",
              "componentType": "CenterProps",
              "content": [
                {
                  "uuid": "cta-card-167",
                  "componentType": "FlexProps",
                  "classes": "bg-gradient-to-r from-primary/10 to-accent/10",
                  "content": [
                    {
                      "uuid": "cta-flex-168",
                      "componentType": "FlexProps",
                      "direction": "column",
                      "gap": "6",
                      "align": "center",
                      "classes": "text-center p-8",
                      "content": [
                        {
                          "uuid": "cta-heading-169",
                          "componentType": "HeadingProps",
                          "level": 3,
                          "text": "Ready to Explore AI Tools?"
                        },
                        {
                          "uuid": "cta-text-170",
                          "componentType": "TextProps",
                          "content": "Join our community to discover the latest AI-powered development tools, share experiences, and learn best practices from fellow developers.",
                          "classes": "text-muted-foreground max-w-2xl"
                        },
                        {
                          "uuid": "cta-buttons-171",
                          "componentType": "FlexProps",
                          "direction": "row",
                          "gap": "4",
                          "content": [
                            {
                              "uuid": "cta-join-172",
                              "componentType": "ButtonProps",
                              "text": "Join Community",
                              "variant": "default",
                              "size": "lg"
                            },
                            {
                              "uuid": "cta-more-173",
                              "componentType": "ButtonProps",
                              "text": "Explore More Articles",
                              "variant": "outline",
                              "size": "lg",
                              "link": {
                                "uuid": "cta-link-174",
                                "componentType": "LinkProps",
                                "href": "/blog",
                                "text": "Explore More Articles"
                              }
                            }
                          ]
                        }
                      ]
                    }
                  ],
                  "direction": "column",
                  "gap": "4"
                }
              ]
            }
          ]
        }
      ]
    }
  ]
}